icswebtracker/__init__.py
icswebtracker/admin.py
icswebtracker/apps.py
icswebtracker/middleware.py
icswebtracker/models.py
icswebtracker-0.1.1.dist-info/METADATA
icswebtracker-0.1.1.dist-info/WHEEL
icswebtracker-0.1.1.dist-info/licenses/LICENSE
icswebtracker-0.1.1.dist-info/RECORD
