Metadata-Version: 2.4
Name: icswebtracker
Version: 0.1.1
Summary: A Django app for tracking website visitors
Project-URL: Homepage, https://github.com/reagon0/icswebtracker
Project-URL: Issues, https://github.com/reagon0/icswebtracker/issues
Author-email: Regan Jones <regan@industrialchannelsolutions.com>
License-Expression: MIT
License-File: LICENSE
Classifier: Framework :: Django
Classifier: Framework :: Django :: 3.2
Classifier: Framework :: Django :: 4.0
Classifier: Framework :: Django :: 4.1
Classifier: Intended Audience :: Developers
Classifier: License :: OSI Approved :: MIT License
Classifier: Operating System :: OS Independent
Classifier: Programming Language :: Python :: 3
Classifier: Topic :: Internet :: WWW/HTTP
Requires-Python: >=3.8
Requires-Dist: django-ipware>=7.0.0
Requires-Dist: django>=3.2
